chromogenic/__init__.py
chromogenic/boot.py
chromogenic/clean.py
chromogenic/common.py
chromogenic/export.py
chromogenic/migrate.py
chromogenic/settings.py
chromogenic/tasks.py
chromogenic/version.py
chromogenic/virt_sysprep.py
chromogenic/drivers/__init__.py
chromogenic/drivers/base.py
chromogenic/drivers/eucalyptus.py
chromogenic/drivers/migration.py
chromogenic/drivers/openstack.py
chromogenic/drivers/virtualbox.py
chromogenic-0.5.4.dist-info/AUTHORS
chromogenic-0.5.4.dist-info/LICENSE
chromogenic-0.5.4.dist-info/METADATA
chromogenic-0.5.4.dist-info/WHEEL
chromogenic-0.5.4.dist-info/top_level.txt
chromogenic-0.5.4.dist-info/RECORD
