Metadata-Version: 2.1
Name: chromogenic
Version: 0.5.4
Summary: A unified imaging interface supporting multiple cloud providers.
Home-page: https://github.com/iPlantCollaborativeOpenSource/chromogenic
Author: iPlant Collaborative
Author-email: atmodevs@gmail.com
License: Apache License, Version 2.0
Platform: UNKNOWN
Classifier: Development Status :: 4 - Beta
Classifier: Intended Audience :: Developers
Classifier: Intended Audience :: Information Technology
Classifier: License :: OSI Approved :: Apache Software License
Classifier: Operating System :: OS Independent
Classifier: Programming Language :: Python
Classifier: Topic :: Software Development :: Libraries
Classifier: Topic :: System
Classifier: Topic :: System :: Distributed Computing
Classifier: Topic :: System :: Systems Administration
Requires-Dist: threepio (==0.2.0)
Requires-Dist: rtwo
Requires-Dist: boto (==2.39.0)
